{
  "annotations": {
    "list": [
      {
        "$$hashKey": "object:1058",
        "builtIn": 1,
        "datasource": "-- Grafana --",
        "enable": true,
        "hide": true,
        "iconColor": "rgba(0, 211, 255, 1)",
        "name": "Annotations & Alerts",
        "target": {
          "limit": 100,
          "matchAny": false,
          "tags": [],
          "type": "dashboard"
        },
        "type": "dashboard"
      }
    ]
  },
  "editable": true,
  "fiscalYearStartMonth": 0,
  "gnetId": 1860,
  "graphTooltip": 0,
  "id": 2,
  "iteration": 1646387281256,
  "links": [
    {
      "icon": "external link",
      "tags": [],
      "title": "GitHub",
      "type": "link",
      "url": "https://github.com/rfrail3/grafana-dashboards"
    },
    {
      "icon": "external link",
      "tags": [],
      "title": "Grafana",
      "type": "link",
      "url": "https://grafana.com/grafana/dashboards/1860"
    }
  ],
  "liveNow": false,
  "panels": [
    {
      "collapsed": false,
      "datasource": {
        "type": "prometheus",
        "uid": "kiKUUOL7z"
      },
      "gridPos": {
        "h": 1,
        "w": 24,
        "x": 0,
        "y": 0
      },
      "id": 261,
      "panels": [],
      "title": "Quick CPU / Mem / Disk",
      "type": "row"
    },
    {
      "datasource": {
        "type": "prometheus",
        "uid": "kiKUUOL7z"
      },
      "description": "Busy state of all CPU cores together",
      "fieldConfig": {
        "defaults": {
          "color": {
            "mode": "thresholds"
          },
          "mappings": [
            {
              "options": {
                "match": "null",
                "result": {
                  "text": "N/A"
                }
              },
              "type": "special"
            }
          ],
          "max": 100,
          "min": 0,
          "thresholds": {
            "mode": "absolute",
            "steps": [
              {
                "color": "rgba(50, 172, 45, 0.97)",
                "value": null
              },
              {
                "color": "rgba(237, 129, 40, 0.89)",
                "value": 85
              },
              {
                "color": "rgba(245, 54, 54, 0.9)",
                "value": 95
              }
            ]
          },
          "unit": "percent"
        },
        "overrides": []
      },
      "gridPos": {
        "h": 4,
        "w": 6,
        "x": 0,
        "y": 1
      },
      "id": 20,
      "links": [],
      "options": {
        "orientation": "horizontal",
        "reduceOptions": {
          "calcs": [
            "lastNotNull"
          ],
          "fields": "",
          "values": false
        },
        "showThresholdLabels": false,
        "showThresholdMarkers": true
      },
      "pluginVersion": "8.4.3",
      "targets": [
        {
          "expr": "(((count(count(node_cpu_seconds_total{instance=\"$node\",job=\"$job\"}) by (cpu))) - avg(sum by (mode)(rate(node_cpu_seconds_total{mode='idle',instance=\"$node\",job=\"$job\"}[$__rate_interval])))) * 100) / count(count(node_cpu_seconds_total{instance=\"$node\",job=\"$job\"}) by (cpu))",
          "hide": false,
          "intervalFactor": 1,
          "legendFormat": "",
          "refId": "A",
          "step": 240
        }
      ],
      "title": "CPU Busy",
      "transparent": true,
      "type": "gauge"
    },
    {
      "datasource": {
        "type": "prometheus",
        "uid": "kiKUUOL7z"
      },
      "description": "Non available RAM memory",
      "fieldConfig": {
        "defaults": {
          "color": {
            "mode": "thresholds"
          },
          "decimals": 0,
          "mappings": [],
          "max": 100,
          "min": 0,
          "thresholds": {
            "mode": "absolute",
            "steps": [
              {
                "color": "rgba(50, 172, 45, 0.97)",
                "value": null
              },
              {
                "color": "rgba(237, 129, 40, 0.89)",
                "value": 80
              },
              {
                "color": "rgba(245, 54, 54, 0.9)",
                "value": 90
              }
            ]
          },
          "unit": "percent"
        },
        "overrides": []
      },
      "gridPos": {
        "h": 4,
        "w": 6,
        "x": 6,
        "y": 1
      },
      "hideTimeOverride": false,
      "id": 16,
      "links": [],
      "options": {
        "orientation": "horizontal",
        "reduceOptions": {
          "calcs": [
            "lastNotNull"
          ],
          "fields": "",
          "values": false
        },
        "showThresholdLabels": false,
        "showThresholdMarkers": true
      },
      "pluginVersion": "8.4.3",
      "targets": [
        {
          "expr": "((node_memory_MemTotal_bytes{instance=\"$node\",job=\"$job\"} - node_memory_MemFree_bytes{instance=\"$node\",job=\"$job\"}) / (node_memory_MemTotal_bytes{instance=\"$node\",job=\"$job\"} )) * 100",
          "format": "time_series",
          "hide": true,
          "intervalFactor": 1,
          "refId": "A",
          "step": 240
        },
        {
          "expr": "100 - ((node_memory_MemAvailable_bytes{instance=\"$node\",job=\"$job\"} * 100) / node_memory_MemTotal_bytes{instance=\"$node\",job=\"$job\"})",
          "format": "time_series",
          "hide": false,
          "intervalFactor": 1,
          "refId": "B",
          "step": 240
        }
      ],
      "title": "RAM Used",
      "transparent": true,
      "type": "gauge"
    },
    {
      "datasource": {
        "type": "prometheus",
        "uid": "kiKUUOL7z"
      },
      "description": "Used Swap",
      "fieldConfig": {
        "defaults": {
          "color": {
            "mode": "thresholds"
          },
          "mappings": [
            {
              "options": {
                "match": "null",
                "result": {
                  "text": "N/A"
                }
              },
              "type": "special"
            }
          ],
          "max": 100,
          "min": 0,
          "thresholds": {
            "mode": "absolute",
            "steps": [
              {
                "color": "rgba(50, 172, 45, 0.97)",
                "value": null
              },
              {
                "color": "rgba(237, 129, 40, 0.89)",
                "value": 10
              },
              {
                "color": "rgba(245, 54, 54, 0.9)",
                "value": 25
              }
            ]
          },
          "unit": "percent"
        },
        "overrides": []
      },
      "gridPos": {
        "h": 4,
        "w": 6,
        "x": 12,
        "y": 1
      },
      "id": 21,
      "links": [],
      "options": {
        "orientation": "horizontal",
        "reduceOptions": {
          "calcs": [
            "lastNotNull"
          ],
          "fields": "",
          "values": false
        },
        "showThresholdLabels": false,
        "showThresholdMarkers": true
      },
      "pluginVersion": "8.4.3",
      "targets": [
        {
          "expr": "((node_memory_SwapTotal_bytes{instance=\"$node\",job=\"$job\"} - node_memory_SwapFree_bytes{instance=\"$node\",job=\"$job\"}) / (node_memory_SwapTotal_bytes{instance=\"$node\",job=\"$job\"} )) * 100",
          "intervalFactor": 1,
          "refId": "A",
          "step": 240
        }
      ],
      "title": "SWAP Used",
      "transparent": true,
      "type": "gauge"
    },
    {
      "datasource": {
        "type": "prometheus",
        "uid": "kiKUUOL7z"
      },
      "description": "Used Root FS",
      "fieldConfig": {
        "defaults": {
          "color": {
            "mode": "thresholds"
          },
          "mappings": [
            {
              "options": {
                "match": "null",
                "result": {
                  "text": "N/A"
                }
              },
              "type": "special"
            }
          ],
          "max": 100,
          "min": 0,
          "thresholds": {
            "mode": "absolute",
            "steps": [
              {
                "color": "rgba(50, 172, 45, 0.97)",
                "value": null
              },
              {
                "color": "rgba(237, 129, 40, 0.89)",
                "value": 80
              },
              {
                "color": "rgba(245, 54, 54, 0.9)",
                "value": 90
              }
            ]
          },
          "unit": "percent"
        },
        "overrides": []
      },
      "gridPos": {
        "h": 4,
        "w": 6,
        "x": 18,
        "y": 1
      },
      "id": 154,
      "links": [],
      "options": {
        "orientation": "horizontal",
        "reduceOptions": {
          "calcs": [
            "lastNotNull"
          ],
          "fields": "",
          "values": false
        },
        "showThresholdLabels": false,
        "showThresholdMarkers": true
      },
      "pluginVersion": "8.4.3",
      "targets": [
        {
          "expr": "100 - ((node_filesystem_avail_bytes{instance=\"$node\",job=\"$job\",mountpoint=\"/\",fstype!=\"rootfs\"} * 100) / node_filesystem_size_bytes{instance=\"$node\",job=\"$job\",mountpoint=\"/\",fstype!=\"rootfs\"})",
          "format": "time_series",
          "intervalFactor": 1,
          "refId": "A",
          "step": 240
        }
      ],
      "title": "Root FS Used",
      "transparent": true,
      "type": "gauge"
    },
    {
      "collapsed": false,
      "datasource": {
        "type": "prometheus",
        "uid": "kiKUUOL7z"
      },
      "gridPos": {
        "h": 1,
        "w": 24,
        "x": 0,
        "y": 5
      },
      "id": 263,
      "panels": [],
      "title": "Basic",
      "type": "row"
    },
    {
      "aliasColors": {
        "Busy": "#EAB839",
        "Busy Iowait": "#890F02",
        "Busy other": "#1F78C1",
        "Idle": "#052B51",
        "Idle - Waiting for something to happen": "#052B51",
        "guest": "#9AC48A",
        "idle": "#052B51",
        "iowait": "#EAB839",
        "irq": "#BF1B00",
        "nice": "#C15C17",
        "softirq": "#E24D42",
        "steal": "#FCE2DE",
        "system": "#508642",
        "user": "#5195CE"
      },
      "bars": false,
      "dashLength": 10,
      "dashes": false,
      "datasource": {
        "type": "prometheus",
        "uid": "kiKUUOL7z"
      },
      "decimals": 2,
      "description": "Basic CPU info",
      "fieldConfig": {
        "defaults": {
          "links": []
        },
        "overrides": []
      },
      "fill": 4,
      "fillGradient": 0,
      "gridPos": {
        "h": 7,
        "w": 12,
        "x": 0,
        "y": 6
      },
      "hiddenSeries": false,
      "id": 77,
      "legend": {
        "alignAsTable": false,
        "avg": false,
        "current": false,
        "max": false,
        "min": false,
        "rightSide": false,
        "show": true,
        "sideWidth": 250,
        "total": false,
        "values": false
      },
      "lines": true,
      "linewidth": 1,
      "links": [],
      "maxPerRow": 6,
      "nullPointMode": "null",
      "options": {
        "alertThreshold": true
      },
      "percentage": true,
      "pluginVersion": "8.4.3",
      "pointradius": 5,
      "points": false,
      "renderer": "flot",
      "seriesOverrides": [
        {
          "alias": "Busy Iowait",
          "color": "#890F02"
        },
        {
          "alias": "Idle",
          "color": "#7EB26D"
        },
        {
          "alias": "Busy System",
          "color": "#EAB839"
        },
        {
          "alias": "Busy User",
          "color": "#0A437C"
        },
        {
          "alias": "Busy Other",
          "color": "#6D1F62"
        }
      ],
      "spaceLength": 10,
      "stack": true,
      "steppedLine": false,
      "targets": [
        {
          "expr": "sum by (instance)(rate(node_cpu_seconds_total{mode=\"system\",instance=\"$node\",job=\"$job\"}[$__rate_interval])) * 100",
          "format": "time_series",
          "hide": false,
          "intervalFactor": 1,
          "legendFormat": "Busy System",
          "refId": "A",
          "step": 240
        },
        {
          "expr": "sum by (instance)(rate(node_cpu_seconds_total{mode='user',instance=\"$node\",job=\"$job\"}[$__rate_interval])) * 100",
          "format": "time_series",
          "hide": false,
          "intervalFactor": 1,
          "legendFormat": "Busy User",
          "refId": "B",
          "step": 240
        },
        {
          "expr": "sum by (instance)(rate(node_cpu_seconds_total{mode='iowait',instance=\"$node\",job=\"$job\"}[$__rate_interval])) * 100",
          "format": "time_series",
          "intervalFactor": 1,
          "legendFormat": "Busy Iowait",
          "refId": "C",
          "step": 240
        },
        {
          "expr": "sum by (instance)(rate(node_cpu_seconds_total{mode=~\".*irq\",instance=\"$node\",job=\"$job\"}[$__rate_interval])) * 100",
          "format": "time_series",
          "intervalFactor": 1,
          "legendFormat": "Busy IRQs",
          "refId": "D",
          "step": 240
        },
        {
          "expr": "sum (rate(node_cpu_seconds_total{mode!='idle',mode!='user',mode!='system',mode!='iowait',mode!='irq',mode!='softirq',instance=\"$node\",job=\"$job\"}[$__rate_interval])) * 100",
          "format": "time_series",
          "intervalFactor": 1,
          "legendFormat": "Busy Other",
          "refId": "E",
          "step": 240
        },
        {
          "expr": "sum by (mode)(rate(node_cpu_seconds_total{mode='idle',instance=\"$node\",job=\"$job\"}[$__rate_interval])) * 100",
          "format": "time_series",
          "intervalFactor": 1,
          "legendFormat": "Idle",
          "refId": "F",
          "step": 240
        }
      ],
      "thresholds": [],
      "timeRegions": [],
      "title": "CPU Basic",
      "tooltip": {
        "shared": true,
        "sort": 0,
        "value_type": "individual"
      },
      "transparent": true,
      "type": "graph",
      "xaxis": {
        "mode": "time",
        "show": true,
        "values": []
      },
      "yaxes": [
        {
          "$$hashKey": "object:123",
          "format": "short",
          "label": "",
          "logBase": 1,
          "max": "100",
          "min": "0",
          "show": true
        },
        {
          "$$hashKey": "object:124",
          "format": "short",
          "logBase": 1,
          "show": false
        }
      ],
      "yaxis": {
        "align": false
      }
    },
    {
      "aliasColors": {
        "Apps": "#629E51",
        "Buffers": "#614D93",
        "Cache": "#6D1F62",
        "Cached": "#511749",
        "Committed": "#508642",
        "Free": "#0A437C",
        "Hardware Corrupted - Amount of RAM that the kernel identified as corrupted / not working": "#CFFAFF",
        "Inactive": "#584477",
        "PageTables": "#0A50A1",
        "Page_Tables": "#0A50A1",
        "RAM_Free": "#E0F9D7",
        "SWAP Used": "#BF1B00",
        "Slab": "#806EB7",
        "Slab_Cache": "#E0752D",
        "Swap": "#BF1B00",
        "Swap Used": "#BF1B00",
        "Swap_Cache": "#C15C17",
        "Swap_Free": "#2F575E",
        "Unused": "#EAB839"
      },
      "bars": false,
      "dashLength": 10,
      "dashes": false,
      "datasource": {
        "type": "prometheus",
        "uid": "kiKUUOL7z"
      },
      "decimals": 2,
      "description": "Basic memory usage",
      "fieldConfig": {
        "defaults": {
          "links": []
        },
        "overrides": []
      },
      "fill": 4,
      "fillGradient": 0,
      "gridPos": {
        "h": 7,
        "w": 12,
        "x": 12,
        "y": 6
      },
      "hiddenSeries": false,
      "id": 78,
      "legend": {
        "alignAsTable": false,
        "avg": false,
        "current": false,
        "max": false,
        "min": false,
        "rightSide": false,
        "show": true,
        "sideWidth": 350,
        "total": false,
        "values": false
      },
      "lines": true,
      "linewidth": 1,
      "links": [],
      "maxPerRow": 6,
      "nullPointMode": "null",
      "options": {
        "alertThreshold": true
      },
      "percentage": false,
      "pluginVersion": "8.4.3",
      "pointradius": 5,
      "points": false,
      "renderer": "flot",
      "seriesOverrides": [
        {
          "alias": "RAM Total",
          "color": "#E0F9D7",
          "fill": 0,
          "stack": false
        },
        {
          "alias": "RAM Cache + Buffer",
          "color": "#052B51"
        },
        {
          "alias": "RAM Free",
          "color": "#7EB26D"
        },
        {
          "alias": "Avaliable",
          "color": "#DEDAF7",
          "fill": 0,
          "stack": false
        }
      ],
      "spaceLength": 10,
      "stack": true,
      "steppedLine": false,
      "targets": [
        {
          "expr": "node_memory_MemTotal_bytes{instance=\"$node\",job=\"$job\"}",
          "format": "time_series",
          "hide": false,
          "intervalFactor": 1,
          "legendFormat": "RAM Total",
          "refId": "A",
          "step": 240
        },
        {
          "expr": "node_memory_MemTotal_bytes{instance=\"$node\",job=\"$job\"} - node_memory_MemFree_bytes{instance=\"$node\",job=\"$job\"} - (node_memory_Cached_bytes{instance=\"$node\",job=\"$job\"} + node_memory_Buffers_bytes{instance=\"$node\",job=\"$job\"})",
          "format": "time_series",
          "hide": false,
          "intervalFactor": 1,
          "legendFormat": "RAM Used",
          "refId": "B",
          "step": 240
        },
        {
          "expr": "node_memory_Cached_bytes{instance=\"$node\",job=\"$job\"} + node_memory_Buffers_bytes{instance=\"$node\",job=\"$job\"}",
          "format": "time_series",
          "intervalFactor": 1,
          "legendFormat": "RAM Cache + Buffer",
          "refId": "C",
          "step": 240
        },
        {
          "expr": "node_memory_MemFree_bytes{instance=\"$node\",job=\"$job\"}",
          "format": "time_series",
          "intervalFactor": 1,
          "legendFormat": "RAM Free",
          "refId": "D",
          "step": 240
        },
        {
          "expr": "(node_memory_SwapTotal_bytes{instance=\"$node\",job=\"$job\"} - node_memory_SwapFree_bytes{instance=\"$node\",job=\"$job\"})",
          "format": "time_series",
          "intervalFactor": 1,
          "legendFormat": "SWAP Used",
          "refId": "E",
          "step": 240
        }
      ],
      "thresholds": [],
      "timeRegions": [],
      "title": "Memory Basic",
      "tooltip": {
        "shared": true,
        "sort": 0,
        "value_type": "individual"
      },
      "transparent": true,
      "type": "graph",
      "xaxis": {
        "mode": "time",
        "show": true,
        "values": []
      },
      "yaxes": [
        {
          "format": "bytes",
          "label": "",
          "logBase": 1,
          "min": "0",
          "show": true
        },
        {
          "format": "short",
          "logBase": 1,
          "show": false
        }
      ],
      "yaxis": {
        "align": false
      }
    },
    {
      "aliasColors": {
        "receive_packets_eth0": "#7EB26D",
        "receive_packets_lo": "#E24D42",
        "transmit_packets_eth0": "#7EB26D",
        "transmit_packets_lo": "#E24D42"
      },
      "bars": false,
      "dashLength": 10,
      "dashes": false,
      "datasource": {
        "type": "prometheus",
        "uid": "kiKUUOL7z"
      },
      "fieldConfig": {
        "defaults": {
          "links": []
        },
        "overrides": []
      },
      "fill": 4,
      "fillGradient": 0,
      "gridPos": {
        "h": 9,
        "w": 12,
        "x": 0,
        "y": 13
      },
      "hiddenSeries": false,
      "id": 84,
      "legend": {
        "alignAsTable": true,
        "avg": true,
        "current": true,
        "max": true,
        "min": true,
        "rightSide": false,
        "show": true,
        "total": false,
        "values": true
      },
      "lines": true,
      "linewidth": 1,
      "links": [],
      "nullPointMode": "null",
      "options": {
        "alertThreshold": true
      },
      "percentage": false,
      "pluginVersion": "8.4.3",
      "pointradius": 5,
      "points": false,
      "renderer": "flot",
      "seriesOverrides": [
        {
          "$$hashKey": "object:5871",
          "alias": "/.*Trans.*/",
          "transform": "negative-Y"
        }
      ],
      "spaceLength": 10,
      "stack": false,
      "steppedLine": false,
      "targets": [
        {
          "expr": "rate(node_network_receive_bytes_total{instance=\"$node\",job=\"$job\"}[$__rate_interval])*8",
          "format": "time_series",
          "intervalFactor": 1,
          "legendFormat": "{{device}} - Receive",
          "refId": "A",
          "step": 240
        },
        {
          "expr": "rate(node_network_transmit_bytes_total{instance=\"$node\",job=\"$job\"}[$__rate_interval])*8",
          "format": "time_series",
          "intervalFactor": 1,
          "legendFormat": "{{device}} - Transmit",
          "refId": "B",
          "step": 240
        }
      ],
      "thresholds": [],
      "timeRegions": [],
      "title": "Network Traffic",
      "tooltip": {
        "shared": true,
        "sort": 0,
        "value_type": "individual"
      },
      "transparent": true,
      "type": "graph",
      "xaxis": {
        "mode": "time",
        "show": true,
        "values": []
      },
      "yaxes": [
        {
          "$$hashKey": "object:5884",
          "format": "bps",
          "label": "bits out (-) / in (+)",
          "logBase": 1,
          "show": true
        },
        {
          "$$hashKey": "object:5885",
          "format": "short",
          "logBase": 1,
          "show": false
        }
      ],
      "yaxis": {
        "align": false
      }
    },
    {
      "collapsed": false,
      "datasource": {
        "type": "prometheus",
        "uid": "kiKUUOL7z"
      },
      "gridPos": {
        "h": 1,
        "w": 24,
        "x": 0,
        "y": 22
      },
      "id": 265,
      "panels": [],
      "title": "Disk",
      "type": "row"
    },
    {
      "aliasColors": {},
      "bars": false,
      "dashLength": 10,
      "dashes": false,
      "datasource": {
        "type": "prometheus",
        "uid": "kiKUUOL7z"
      },
      "description": "",
      "fieldConfig": {
        "defaults": {
          "links": []
        },
        "overrides": []
      },
      "fill": 2,
      "fillGradient": 0,
      "gridPos": {
        "h": 8,
        "w": 11,
        "x": 0,
        "y": 23
      },
      "hiddenSeries": false,
      "id": 229,
      "legend": {
        "alignAsTable": true,
        "avg": true,
        "current": true,
        "hideZero": true,
        "max": true,
        "min": true,
        "rightSide": false,
        "show": true,
        "total": false,
        "values": true
      },
      "lines": true,
      "linewidth": 1,
      "links": [],
      "maxPerRow": 6,
      "nullPointMode": "null",
      "options": {
        "alertThreshold": true
      },
      "percentage": false,
      "pluginVersion": "8.4.3",
      "pointradius": 5,
      "points": false,
      "renderer": "flot",
      "seriesOverrides": [
        {
          "alias": "/.*Read.*/",
          "transform": "negative-Y"
        },
        {
          "alias": "/.*sda_.*/",
          "color": "#7EB26D"
        },
        {
          "alias": "/.*sdb_.*/",
          "color": "#EAB839"
        },
        {
          "alias": "/.*sdc_.*/",
          "color": "#6ED0E0"
        },
        {
          "alias": "/.*sdd_.*/",
          "color": "#EF843C"
        },
        {
          "alias": "/.*sde_.*/",
          "color": "#E24D42"
        },
        {
          "alias": "/.*sda1.*/",
          "color": "#584477"
        },
        {
          "alias": "/.*sda2_.*/",
          "color": "#BA43A9"
        },
        {
          "alias": "/.*sda3_.*/",
          "color": "#F4D598"
        },
        {
          "alias": "/.*sdb1.*/",
          "color": "#0A50A1"
        },
        {
          "alias": "/.*sdb2.*/",
          "color": "#BF1B00"
        },
        {
          "alias": "/.*sdb2.*/",
          "color": "#BF1B00"
        },
        {
          "alias": "/.*sdb3.*/",
          "color": "#E0752D"
        },
        {
          "alias": "/.*sdc1.*/",
          "color": "#962D82"
        },
        {
          "alias": "/.*sdc2.*/",
          "color": "#614D93"
        },
        {
          "alias": "/.*sdc3.*/",
          "color": "#9AC48A"
        },
        {
          "alias": "/.*sdd1.*/",
          "color": "#65C5DB"
        },
        {
          "alias": "/.*sdd2.*/",
          "color": "#F9934E"
        },
        {
          "alias": "/.*sdd3.*/",
          "color": "#EA6460"
        },
        {
          "alias": "/.*sde1.*/",
          "color": "#E0F9D7"
        },
        {
          "alias": "/.*sdd2.*/",
          "color": "#FCEACA"
        },
        {
          "alias": "/.*sde3.*/",
          "color": "#F9E2D2"
        }
      ],
      "spaceLength": 10,
      "stack": false,
      "steppedLine": false,
      "targets": [
        {
          "expr": "rate(node_disk_reads_completed_total{instance=\"$node\",job=\"$job\",device=~\"$diskdevices\"}[$__rate_interval])",
          "intervalFactor": 4,
          "legendFormat": "{{device}} - Reads completed",
          "refId": "A",
          "step": 240
        },
        {
          "expr": "rate(node_disk_writes_completed_total{instance=\"$node\",job=\"$job\",device=~\"$diskdevices\"}[$__rate_interval])",
          "intervalFactor": 1,
          "legendFormat": "{{device}} - Writes completed",
          "refId": "B",
          "step": 240
        }
      ],
      "thresholds": [],
      "timeRegions": [],
      "title": "Disk IOps",
      "tooltip": {
        "shared": false,
        "sort": 0,
        "value_type": "individual"
      },
      "transparent": true,
      "type": "graph",
      "xaxis": {
        "mode": "time",
        "show": true,
        "values": []
      },
      "yaxes": [
        {
          "format": "iops",
          "label": "IO read (-) / write (+)",
          "logBase": 1,
          "show": true
        },
        {
          "format": "short",
          "logBase": 1,
          "show": false
        }
      ],
      "yaxis": {
        "align": false
      }
    },
    {
      "aliasColors": {
        "io time": "#890F02"
      },
      "bars": false,
      "dashLength": 10,
      "dashes": false,
      "datasource": {
        "type": "prometheus",
        "uid": "kiKUUOL7z"
      },
      "decimals": 3,
      "description": "",
      "fieldConfig": {
        "defaults": {
          "links": []
        },
        "overrides": []
      },
      "fill": 4,
      "fillGradient": 0,
      "gridPos": {
        "h": 8,
        "w": 12,
        "x": 12,
        "y": 23
      },
      "hiddenSeries": false,
      "id": 42,
      "legend": {
        "alignAsTable": true,
        "avg": true,
        "current": true,
        "max": true,
        "min": true,
        "rightSide": false,
        "show": true,
        "total": false,
        "values": true
      },
      "lines": true,
      "linewidth": 1,
      "links": [],
      "maxPerRow": 6,
      "nullPointMode": "null",
      "options": {
        "alertThreshold": true
      },
      "percentage": false,
      "pluginVersion": "8.4.3",
      "pointradius": 5,
      "points": false,
      "renderer": "flot",
      "seriesOverrides": [
        {
          "alias": "/.*read*./",
          "transform": "negative-Y"
        },
        {
          "alias": "/.*sda.*/",
          "color": "#7EB26D"
        },
        {
          "alias": "/.*sdb.*/",
          "color": "#EAB839"
        },
        {
          "alias": "/.*sdc.*/",
          "color": "#6ED0E0"
        },
        {
          "alias": "/.*sdd.*/",
          "color": "#EF843C"
        },
        {
          "alias": "/.*sde.*/",
          "color": "#E24D42"
        }
      ],
      "spaceLength": 10,
      "stack": false,
      "steppedLine": false,
      "targets": [
        {
          "expr": "rate(node_disk_read_bytes_total{instance=\"$node\",job=\"$job\",device=~\"$diskdevices\"}[$__rate_interval])",
          "format": "time_series",
          "hide": false,
          "intervalFactor": 1,
          "legendFormat": "{{device}} - Successfully read bytes",
          "refId": "A",
          "step": 240
        },
        {
          "expr": "rate(node_disk_written_bytes_total{instance=\"$node\",job=\"$job\",device=~\"$diskdevices\"}[$__rate_interval])",
          "format": "time_series",
          "hide": false,
          "intervalFactor": 1,
          "legendFormat": "{{device}} - Successfully written bytes",
          "refId": "B",
          "step": 240
        }
      ],
      "thresholds": [],
      "timeRegions": [],
      "title": "I/O Usage Read / Write",
      "tooltip": {
        "shared": true,
        "sort": 0,
        "value_type": "individual"
      },
      "transparent": true,
      "type": "graph",
      "xaxis": {
        "mode": "time",
        "show": false,
        "values": []
      },
      "yaxes": [
        {
          "$$hashKey": "object:965",
          "format": "Bps",
          "label": "bytes read (-) / write (+)",
          "logBase": 1,
          "show": true
        },
        {
          "$$hashKey": "object:966",
          "format": "ms",
          "label": "",
          "logBase": 1,
          "show": true
        }
      ],
      "yaxis": {
        "align": false
      }
    },
    {
      "collapsed": false,
      "datasource": {
        "type": "prometheus",
        "uid": "kiKUUOL7z"
      },
      "gridPos": {
        "h": 1,
        "w": 24,
        "x": 0,
        "y": 31
      },
      "id": 271,
      "panels": [],
      "title": "Storage Filesystem",
      "type": "row"
    },
    {
      "aliasColors": {},
      "bars": false,
      "dashLength": 10,
      "dashes": false,
      "datasource": {
        "type": "prometheus",
        "uid": "kiKUUOL7z"
      },
      "decimals": 3,
      "description": "",
      "fieldConfig": {
        "defaults": {
          "links": []
        },
        "overrides": []
      },
      "fill": 2,
      "fillGradient": 0,
      "gridPos": {
        "h": 10,
        "w": 12,
        "x": 0,
        "y": 32
      },
      "hiddenSeries": false,
      "id": 43,
      "legend": {
        "alignAsTable": true,
        "avg": true,
        "current": true,
        "max": true,
        "min": true,
        "rightSide": false,
        "show": true,
        "total": false,
        "values": true
      },
      "lines": true,
      "linewidth": 1,
      "links": [],
      "maxPerRow": 6,
      "nullPointMode": "null",
      "options": {
        "alertThreshold": true
      },
      "percentage": false,
      "pluginVersion": "8.4.3",
      "pointradius": 5,
      "points": false,
      "renderer": "flot",
      "seriesOverrides": [],
      "spaceLength": 10,
      "stack": false,
      "steppedLine": false,
      "targets": [
        {
          "expr": "node_filesystem_avail_bytes{instance=\"$node\",job=\"$job\",device!~'rootfs'}",
          "format": "time_series",
          "hide": false,
          "intervalFactor": 1,
          "legendFormat": "{{mountpoint}} - Available",
          "metric": "",
          "refId": "A",
          "step": 240
        },
        {
          "expr": "node_filesystem_free_bytes{instance=\"$node\",job=\"$job\",device!~'rootfs'}",
          "format": "time_series",
          "hide": true,
          "intervalFactor": 1,
          "legendFormat": "{{mountpoint}} - Free",
          "refId": "B",
          "step": 240
        },
        {
          "expr": "node_filesystem_size_bytes{instance=\"$node\",job=\"$job\",device!~'rootfs'}",
          "format": "time_series",
          "hide": true,
          "intervalFactor": 1,
          "legendFormat": "{{mountpoint}} - Size",
          "refId": "C",
          "step": 240
        }
      ],
      "thresholds": [],
      "timeRegions": [],
      "title": "Filesystem space available",
      "tooltip": {
        "shared": true,
        "sort": 0,
        "value_type": "individual"
      },
      "transparent": true,
      "type": "graph",
      "xaxis": {
        "mode": "time",
        "show": true,
        "values": []
      },
      "yaxes": [
        {
          "$$hashKey": "object:3826",
          "format": "bytes",
          "label": "bytes",
          "logBase": 1,
          "min": "0",
          "show": true
        },
        {
          "$$hashKey": "object:3827",
          "format": "short",
          "logBase": 1,
          "show": false
        }
      ],
      "yaxis": {
        "align": false
      }
    },
    {
      "aliasColors": {
        "/ ReadOnly": "#890F02"
      },
      "bars": false,
      "dashLength": 10,
      "dashes": false,
      "datasource": {
        "type": "prometheus",
        "uid": "kiKUUOL7z"
      },
      "description": "",
      "fieldConfig": {
        "defaults": {
          "links": []
        },
        "overrides": []
      },
      "fill": 2,
      "fillGradient": 0,
      "gridPos": {
        "h": 10,
        "w": 12,
        "x": 12,
        "y": 32
      },
      "hiddenSeries": false,
      "id": 44,
      "legend": {
        "alignAsTable": true,
        "avg": true,
        "current": true,
        "hideEmpty": true,
        "hideZero": true,
        "max": true,
        "min": true,
        "rightSide": false,
        "show": true,
        "total": false,
        "values": true
      },
      "lines": true,
      "linewidth": 1,
      "links": [],
      "maxPerRow": 6,
      "nullPointMode": "null",
      "options": {
        "alertThreshold": true
      },
      "percentage": false,
      "pluginVersion": "8.4.3",
      "pointradius": 5,
      "points": false,
      "renderer": "flot",
      "seriesOverrides": [],
      "spaceLength": 10,
      "stack": true,
      "steppedLine": false,
      "targets": [
        {
          "expr": "node_filesystem_readonly{instance=\"$node\",job=\"$job\",device!~'rootfs'}",
          "format": "time_series",
          "intervalFactor": 1,
          "legendFormat": "{{mountpoint}} - ReadOnly",
          "refId": "A",
          "step": 240
        },
        {
          "expr": "node_filesystem_device_error{instance=\"$node\",job=\"$job\",device!~'rootfs',fstype!~'tmpfs'}",
          "format": "time_series",
          "interval": "",
          "intervalFactor": 1,
          "legendFormat": "{{mountpoint}} - Device error",
          "refId": "B",
          "step": 240
        }
      ],
      "thresholds": [],
      "timeRegions": [],
      "title": "Filesystem in ReadOnly / Error",
      "tooltip": {
        "shared": true,
        "sort": 0,
        "value_type": "individual"
      },
      "transparent": true,
      "type": "graph",
      "xaxis": {
        "mode": "time",
        "show": true,
        "values": []
      },
      "yaxes": [
        {
          "$$hashKey": "object:3670",
          "format": "short",
          "label": "counter",
          "logBase": 1,
          "max": "1",
          "min": "0",
          "show": true
        },
        {
          "$$hashKey": "object:3671",
          "format": "short",
          "logBase": 1,
          "show": false
        }
      ],
      "yaxis": {
        "align": false
      }
    },
    {
      "collapsed": false,
      "datasource": {
        "type": "prometheus",
        "uid": "kiKUUOL7z"
      },
      "gridPos": {
        "h": 1,
        "w": 24,
        "x": 0,
        "y": 42
      },
      "id": 279,
      "panels": [],
      "title": "Node Exporter",
      "type": "row"
    },
    {
      "aliasColors": {},
      "bars": false,
      "dashLength": 10,
      "dashes": false,
      "datasource": {
        "type": "prometheus",
        "uid": "kiKUUOL7z"
      },
      "description": "",
      "fieldConfig": {
        "defaults": {
          "links": []
        },
        "overrides": []
      },
      "fill": 2,
      "fillGradient": 0,
      "gridPos": {
        "h": 10,
        "w": 12,
        "x": 0,
        "y": 43
      },
      "hiddenSeries": false,
      "id": 40,
      "legend": {
        "alignAsTable": true,
        "avg": true,
        "current": true,
        "max": true,
        "min": true,
        "show": true,
        "sort": "current",
        "sortDesc": true,
        "total": false,
        "values": true
      },
      "lines": true,
      "linewidth": 1,
      "links": [],
      "nullPointMode": "null",
      "options": {
        "alertThreshold": true
      },
      "percentage": false,
      "pluginVersion": "8.4.3",
      "pointradius": 5,
      "points": false,
      "renderer": "flot",
      "seriesOverrides": [],
      "spaceLength": 10,
      "stack": true,
      "steppedLine": false,
      "targets": [
        {
          "expr": "node_scrape_collector_duration_seconds{instance=\"$node\",job=\"$job\"}",
          "format": "time_series",
          "hide": false,
          "interval": "",
          "intervalFactor": 1,
          "legendFormat": "{{collector}} - Scrape duration",
          "refId": "A",
          "step": 240
        }
      ],
      "thresholds": [],
      "timeRegions": [],
      "title": "Node Exporter Scrape Time",
      "tooltip": {
        "shared": true,
        "sort": 0,
        "value_type": "individual"
      },
      "transparent": true,
      "type": "graph",
      "xaxis": {
        "mode": "time",
        "show": true,
        "values": []
      },
      "yaxes": [
        {
          "format": "s",
          "label": "seconds",
          "logBase": 1,
          "show": true
        },
        {
          "format": "short",
          "logBase": 1,
          "show": false
        }
      ],
      "yaxis": {
        "align": false
      }
    },
    {
      "aliasColors": {},
      "bars": false,
      "dashLength": 10,
      "dashes": false,
      "datasource": {
        "type": "prometheus",
        "uid": "kiKUUOL7z"
      },
      "description": "",
      "fieldConfig": {
        "defaults": {
          "links": []
        },
        "overrides": []
      },
      "fill": 2,
      "fillGradient": 0,
      "gridPos": {
        "h": 10,
        "w": 12,
        "x": 12,
        "y": 43
      },
      "hiddenSeries": false,
      "id": 157,
      "legend": {
        "alignAsTable": true,
        "avg": true,
        "current": true,
        "max": true,
        "min": true,
        "show": true,
        "total": false,
        "values": true
      },
      "lines": true,
      "linewidth": 1,
      "links": [],
      "nullPointMode": "null",
      "options": {
        "alertThreshold": true
      },
      "percentage": false,
      "pluginVersion": "8.4.3",
      "pointradius": 5,
      "points": false,
      "renderer": "flot",
      "seriesOverrides": [
        {
          "$$hashKey": "object:1969",
          "alias": "/.*error.*/",
          "color": "#F2495C",
          "transform": "negative-Y"
        }
      ],
      "spaceLength": 10,
      "stack": true,
      "steppedLine": false,
      "targets": [
        {
          "expr": "node_scrape_collector_success{instance=\"$node\",job=\"$job\"}",
          "format": "time_series",
          "hide": false,
          "interval": "",
          "intervalFactor": 1,
          "legendFormat": "{{collector}} - Scrape success",
          "refId": "A",
          "step": 240
        },
        {
          "expr": "node_textfile_scrape_error{instance=\"$node\",job=\"$job\"}",
          "format": "time_series",
          "hide": false,
          "interval": "",
          "intervalFactor": 1,
          "legendFormat": "{{collector}} - Scrape textfile error (1 = true)",
          "refId": "B",
          "step": 240
        }
      ],
      "thresholds": [],
      "timeRegions": [],
      "title": "Node Exporter Scrape",
      "tooltip": {
        "shared": true,
        "sort": 0,
        "value_type": "individual"
      },
      "transparent": true,
      "type": "graph",
      "xaxis": {
        "mode": "time",
        "show": true,
        "values": []
      },
      "yaxes": [
        {
          "$$hashKey": "object:1484",
          "format": "short",
          "label": "counter",
          "logBase": 1,
          "show": true
        },
        {
          "$$hashKey": "object:1485",
          "format": "short",
          "logBase": 1,
          "show": false
        }
      ],
      "yaxis": {
        "align": false
      }
    }
  ],
  "refresh": "1m",
  "schemaVersion": 35,
  "style": "dark",
  "tags": [
    "linux"
  ],
  "templating": {
    "list": [
      {
        "current": {
          "selected": false,
          "text": "default",
          "value": "default"
        },
        "hide": 0,
        "includeAll": false,
        "label": "datasource",
        "multi": false,
        "name": "DS_PROMETHEUS",
        "options": [],
        "query": "prometheus",
        "refresh": 1,
        "regex": "",
        "skipUrlSync": false,
        "type": "datasource"
      },
      {
        "current": {
          "selected": true,
          "text": "qbittorrent",
          "value": "qbittorrent"
        },
        "datasource": {
          "type": "prometheus",
          "uid": "kiKUUOL7z"
        },
        "definition": "",
        "hide": 0,
        "includeAll": false,
        "label": "Job",
        "multi": false,
        "name": "job",
        "options": [],
        "query": {
          "query": "label_values(node_uname_info, job)",
          "refId": "Prometheus-job-Variable-Query"
        },
        "refresh": 1,
        "regex": "",
        "skipUrlSync": false,
        "sort": 1,
        "tagValuesQuery": "",
        "tagsQuery": "",
        "type": "query",
        "useTags": false
      },
      {
        "current": {
          "selected": false,
          "text": "node-exporter:9100",
          "value": "node-exporter:9100"
        },
        "datasource": {
          "type": "prometheus",
          "uid": "kiKUUOL7z"
        },
        "definition": "label_values(node_uname_info{job=\"$job\"}, instance)",
        "hide": 0,
        "includeAll": false,
        "label": "Host:",
        "multi": false,
        "name": "node",
        "options": [],
        "query": {
          "query": "label_values(node_uname_info{job=\"$job\"}, instance)",
          "refId": "Prometheus-node-Variable-Query"
        },
        "refresh": 1,
        "regex": "",
        "skipUrlSync": false,
        "sort": 1,
        "tagValuesQuery": "",
        "tagsQuery": "",
        "type": "query",
        "useTags": false
      },
      {
        "current": {
          "selected": false,
          "text": "[a-z]+|nvme[0-9]+n[0-9]+|mmcblk[0-9]+",
          "value": "[a-z]+|nvme[0-9]+n[0-9]+|mmcblk[0-9]+"
        },
        "hide": 2,
        "includeAll": false,
        "multi": false,
        "name": "diskdevices",
        "options": [
          {
            "selected": true,
            "text": "[a-z]+|nvme[0-9]+n[0-9]+|mmcblk[0-9]+",
            "value": "[a-z]+|nvme[0-9]+n[0-9]+|mmcblk[0-9]+"
          }
        ],
        "query": "[a-z]+|nvme[0-9]+n[0-9]+|mmcblk[0-9]+",
        "skipUrlSync": false,
        "type": "custom"
      }
    ]
  },
  "time": {
    "from": "now-24h",
    "to": "now"
  },
  "timepicker": {
    "refresh_intervals": [
      "5s",
      "10s",
      "30s",
      "1m",
      "5m",
      "15m",
      "30m",
      "1h",
      "2h",
      "1d"
    ],
    "time_options": [
      "5m",
      "15m",
      "1h",
      "6h",
      "12h",
      "24h",
      "2d",
      "7d",
      "30d"
    ]
  },
  "timezone": "browser",
  "title": "Node Exporter",
  "uid": "rYdddlPWk",
  "version": 11,
  "weekStart": ""
}